org/__init__.py
org/codeforrussia/__init__.py
org/codeforrussia/selector/__init__.py
org/codeforrussia/selector/beam/__init__.py
org/codeforrussia/selector/beam/pipeline.py
selector_standardization_beam-0.4.15.dist-info/LICENSE
selector_standardization_beam-0.4.15.dist-info/METADATA
selector_standardization_beam-0.4.15.dist-info/WHEEL
selector_standardization_beam-0.4.15.dist-info/top_level.txt
selector_standardization_beam-0.4.15.dist-info/RECORD
