Metadata-Version: 2.1
Name: selector-standardization-beam
Version: 0.4.15
Summary: Data Standardization pipeline in Apache Beam for Selector project
Home-page: https://github.com/Code-for-Russia/selector-pipeline
Author: Nikita Zhiltsov
Author-email: mail@codeforrussia.org
License: UNKNOWN
Project-URL: Bug Tracker, https://github.com/Code-for-Russia/selector-pipeline/issues
Platform: UNKNOWN
Classifier: Programming Language :: Python :: 3
Classifier: License :: OSI Approved :: MIT License
Classifier: Operating System :: OS Independent
Requires-Python: >=3.7
License-File: LICENSE
Requires-Dist: pytest (>=6.2.4)
Requires-Dist: fastavro (>=1.4.0)
Requires-Dist: apache-beam (>=2.20.0)
Requires-Dist: selector-standardizers (>=0.8.3)
